Workbook

Sheet Abstract
A1: ANNEXURE FOR PROCESS MILL CIVIL WORKS AT KHAMMAM PROPOSED PLANT
A2: FROM | B2: RECOMAX ENGINEERING PVT LTD Plot No.257, Flat No.201, Vivekananda Nagar Colony, Kukatpally, Hyderabad GSTIN/UIN: 36AAJCR4002K1ZE State Name : Telangana, Code : 36
A3: TO | B3: GODREJ AGROVET LIMITED, PO No: 6700010232 Building No./Flat No.:4-29/2 Road/Street:R.Sy.No:381/2/2 Locality/Sub Locality: Konijerla Mandal City/Town/Village:Gubbagurthy District: Khammam State Name :Telangana, Pin Code :507165 GSTIN/UIN : 36AAACG0617Q1ZH
B4: PO No: TG/CAPEX/2025-26/10 | E4: Final Price | G4: RA-01
A5: ITEM | B5: DESCRIPTION | C5: UNIT | D5: TOTAL QUANTITY | E5: PO Price | F5: PO Total (Rs.) | G5: Qty | H5: Total (Rs.)
A7: EXC | B7: EXCAVATION
A8: EXC.1 | B8: EXCAVATION FOR FOUNDATION PITS, TRENCHES ETC.
A9: EXC.1A | B9: FOR DEPTH UPTO 1.5M | C9: M3 | D9: =[1]SUMMARY!E12 -> 158.8825 | E9: 200 | F9: =D9*E9 -> 31776.5 | G9: =Excavation!J10 -> 351.7488 | H9: =G9*E9 -> 70349.76
A10: EXC.1B | B10: FOR DEPTH - 1.5M TO 3.0M | C10: M3 | D10: =[1]SUMMARY!E13 -> 90.947 | E10: 270 | F10: =D10*E10 -> 24555.69 | G10: =Excavation!J20 -> 308.36645 | H10: =G10*E10 -> 83258.941
A11: EXC.1C | B11: FOR DEPTH - 3.0M TO 4.5 M. | C11: M3 | D11: =[1]SUMMARY!E14 -> 26.47 | E11: 350 | F11: =D11*E11 -> 9264.5 | H11: =G11*E11 -> 0
A12: EXC.1E | B12: TOP SOIL REMOVALWITH DEPTH NOT MORE THAN 300MM | C12: M2 | D12: =[1]SUMMARY!E16 -> 300 | E12: 120 | F12: =D12*E12 -> 36000 | H12: =G12*E12 -> 0
A13: EXC.4 | B13: CARTING MATERIAL FROM SITE (2 KM RADIUS) | C13: M3 | D13: =[1]SUMMARY!E17 -> 86.444925 | E13: 135 | F13: =D13*E13 -> 11670.065 | H13: =G13*E13 -> 0
A14: EXC.5 | B14: Filling for average height more than 750 mm in plinth | C14: M3 | D14: 1856 | E14: 550 | F14: =D14*E14 -> 1020800 | H14: =G14*E14 -> 0
A15: EXC.7 | B15: SUPPLY-FILL-COMPACT SAND BROUGHT FROM OUTSIDE | D15: 0 | F15: =D15*E15 -> 0 | H15: =G15*E15 -> 0
A16: EXC.7A | B16: FOR FINE SAND | C16: M3 | D16: =[1]SUMMARY!E20 -> 0 | F16: =D16*E16 -> 0 | H16: =G16*E16 -> 0
A17: EXC.7C | B17: FOR SAND GRAVEL | C17: M3 | D17: =[1]SUMMARY!E21 -> 0 | F17: =D17*E17 -> 0 | H17: =G17*E17 -> 0
A18: EXC.9 | B18: ANTITERMITE TREATMENT | C18: M2 | D18: 0 | F18: =D18*E18 -> 0 | H18: =G18*E18 -> 0
D19: 0 | F19: =D19*E19 -> 0 | H19: =G19*E19 -> 0
A20: CON | B20: CONCRETE | D20: 0 | F20: =D20*E20 -> 0 | H20: =G20*E20 -> 0
A21: CON.1 | B21: PLAIN CEMENT CONCRETE | D21: 0 | F21: =D21*E21 -> 0 | H21: =G21*E21 -> 0
A22: CON.1B | B22: AS PER CON.1 1:4:8 P.C.C. | C22: M3 | D22: =[1]SUMMARY!E24 -> 40.261875 | E22: 6000 | F22: =D22*E22 -> 241571.25 | G22: ='Pcc & Rcc'!G30 -> 28.44829 | H22: =G22*E22 -> 170689.74
A23: CON.1D | B23: AS PER CON.1 1:2:4 P.C.C. | C23: M3 | D23: =[1]SUMMARY!E26 -> 3.375 | E23: 6500 | F23: =D23*E23 -> 21937.5 | H23: =G23*E23 -> 0
A24: CON.3 | B24: M20 CONC. IN FOUNDATIONS, PEDESTALS, COLUMNS, BEAMS, COPINGS, WALLS, SLABS, SHELVES, STAIRS ETC. | D24: 0 | F24: =D24*E24 -> 0 | H24: =G24*E24 -> 0
A25: CON.3A | B25: AT AND BELOW PLINTH LEVEL | C25: M3 | D25: =[1]SUMMARY!E31 -> 96.559 | E25: 7000 | F25: =D25*E25 -> 675913 | G25: ='Pcc & Rcc'!G62 -> 149.46197 | H25: =G25*E25 -> 1046233.8
A26: CON.3B | B26: PLINTH TO 4.5 M | C26: M3 | D26: =[1]SUMMARY!E32 -> 59.551 | E26: 7200 | F26: =D26*E26 -> 428767.2 | G26: ='Pcc & Rcc'!G87 -> 25.19398 | H26: =G26*E26 -> 181396.66
A27: CON.3C | B27: 4.5 M TO 9.0 M ABOVE PLINTH LEVEL | C27: M3 | D27: =[1]SUMMARY!E33 -> 0 | F27: =D27*E27 -> 0 | H27: =G27*E27 -> 0
A28: CON.4 | B28: M20 CONC.IN MACHINE FOUNDATIONS | C28: M3 | D28: 0 | F28: =D28*E28 -> 0 | H28: =G28*E28 -> 0
A29: CON.5 | B29: CONCRETE GRADE HIGHER THAN M20 | D29: 0 | F29: =D29*E29 -> 0 | H29: =G29*E29 -> 0
A30: CON.5A | B30: EXTRA OVER M20 FOR M25 (ONLY ADDITIONAL COST FOR PROVIDING M25 GRADE OVER M20 GRADE SHOULD BE CONSIDERED) | C30: M3 | D30: =[1]SUMMARY!E35 -> 156.11 | E30: 800 | F30: =D30*E30 -> 124888 | G30: =G26+G25 -> 174.65595 | H30: =G30*E30 -> 139724.76
A31: CON.6 | B31: EXTRA OVER ITEM CON.3 AND CON.5 FOR USING TREMIX OR EQUIVALENT (ONLY ADDITIONAL COST FOR TREMIX FLOORS SHOULD BE CONSIDERED, CONCRETE IS INCLUDED IN ITEM CON.3) | D31: 0 | F31: =D31*E31 -> 0 | H31: =G31*E31 -> 0
A32: CON.6C | B32: FOR 150 THICK | C32: M2 | D32: =[1]SUMMARY!E37 -> 0 | F32: =D32*E32 -> 0 | H32: =G32*E32 -> 0
A33: CON.6C | B33: FOR 100 THICK | C33: M2 | D33: 0 | F33: =D33*E33 -> 0 | H33: =G33*E33 -> 0
A34: CON.9 | B34: CEMENT GROUT | D34: 0 | F34: =D34*E34 -> 0 | H34: =G34*E34 -> 0
A35: CON.9A | B35: AS PER CON.9 BUT "SHRINKKOMP" OF ACC OR EQUI. NON SHRINK GROUTING | C35: M3 | D35: =[1]SUMMARY!E39 -> 2.625 | E35: =62000*105% -> 65100 | F35: =D35*E35 -> 170887.5 | H35: =G35*E35 -> 0
A36: CON.51 | B36: DISMANTLING RCC WORK | C36: M3 | D36: =[1]SUMMARY!E40 -> 1 | E36: 7000 | F36: =D36*E36 -> 7000 | H36: =G36*E36 -> 0
A37: CON.57 | B37: CORE CUTTING IN EXISTING CONCRETE (300 MM DEPTH) | D37: 0 | F37: =D37*E37 -> 0 | H37: =G37*E37 -> 0
A38: CON.57A | B38: 50 MM DIA. | C38: NO | D38: =[1]SUMMARY!E42 -> 1 | E38: 2500 | F38: =D38*E38 -> 2500 | H38: =G38*E38 -> 0
A39: CON.57B | B39: 75 MM DIA | C39: NO | D39: =[1]SUMMARY!E43 -> 1 | E39: 2500 | F39: =D39*E39 -> 2500 | H39: =G39*E39 -> 0
A40: CON.57C | B40: 100 MM DIA | C40: NO | D40: =[1]SUMMARY!E44 -> 1 | E40: 3000 | F40: =D40*E40 -> 3000 | H40: =G40*E40 -> 0
A41: CON.59 | B41: CUTOUT IN CONCRETE | D41: 0 | F41: =D41*E41 -> 0 | H41: =G41*E41 -> 0
A42: CON.59A | B42: UPTO 0.250 M2 | C42: NO | D42: =[1]SUMMARY!E46 -> 1 | E42: 3000 | F42: =D42*E42 -> 3000 | H42: =G42*E42 -> 0
H43: =G43*E43 -> 0
A44: CON.59B | B44: FROM 0.250 M2 TO 0.500 M2 | C44: NO | D44: =[1]SUMMARY!E47 -> 1 | E44: 5000 | F44: =D44*E44 -> 5000 | H44: =G44*E44 -> 0
A45: CON.59C | B45: FROM 0.500 M2 TO 1.0 M2 | C45: NO | D45: =[1]SUMMARY!E48 -> 1 | E45: 9000 | F45: =D45*E45 -> 9000 | H45: =G45*E45 -> 0
D46: 0 | F46: =D46*E46 -> 0 | H46: =G46*E46 -> 0
A47: FW | B47: FORMWORK | D47: 0 | F47: =D47*E47 -> 0 | H47: =G47*E47 -> 0
A48: FW.1 | B48: ORDINARY FINISH FOR CONCRETE WORK | D48: 0 | F48: =D48*E48 -> 0 | H48: =G48*E48 -> 0
A49: FW.1A | B49: AT AND BELOW PLINTH | C49: M2 | D49: =[1]SUMMARY!E51 -> 1308.8 | E49: 600 | F49: =D49*E49 -> 785280 | G49: =Shuttering!G32+Shuttering!G10 -> 248.484 | H49: =G49*E49 -> 149090.4
A50: FW.1B | B50: PLINTH TO 4.5M | C50: M2 | D50: =[1]SUMMARY!E52 -> 577.32 | E50: 650 | F50: =D50*E50 -> 375258 | G50: =Shuttering!G59 -> 162.1132 | H50: =G50*E50 -> 105373.58
A51: FW.1C | B51: 4.5 M TO 9.0 M FROM PLINTH LEVEL | C51: M2 | D51: =[1]SUMMARY!E53 -> 0 | F51: =D51*E51 -> 0 | H51: =G51*E51 -> 0
A52: FW.4 | B52: EXTRA OVER FW.1 BUT FOR CIRCULAR SHUTTERING OF ANY RADIUS AND AT ANY HEIGHT (ONLY ADDITIONAL COST FOR CIRCULAR SHUTTERING SHOULD BE CONSIDERED) | C52: M2 | D52: 0 | F52: =D52*E52 -> 0 | H52: =G52*E52 -> 0
A53: FW.5 | B53: EXTRA OVER FW.1 FOR PROVIDING STAGING OF HEIGHT MORE THAN 4.5M FROM FINISH FLOOR LEVEL (ONLY ADDITIONAL COST FOR STAGING SHOULD BE CONSIDERED) | C53: M2 | D53: 0 | F53: =D53*E53 -> 0 | H53: =G53*E53 -> 0
A54: FW.7 | B54: FORMING POCKET-CUTOUT ETC. | D54: 0 | F54: =D54*E54 -> 0 | H54: =G54*E54 -> 0
A55: FW.7A | B55: C. S. AREA (UPTO 100 CM2) | C55: M | D55: =[1]SUMMARY!E55 -> 1.03 | E55: 1250 | F55: =D55*E55 -> 1287.5 | H55: =G55*E55 -> 0
A56: FW.7B | B56: C. S. AREA (100-250 CM2) | C56: M | D56: =[1]SUMMARY!E56 -> 1.03 | E56: 1400 | F56: =D56*E56 -> 1442 | H56: =G56*E56 -> 0
A57: FW.8 | B57: FILLER BOARD FOR EXPANSION JOINT | D57: 0 | F57: =D57*E57 -> 0 | H57: =G57*E57 -> 0
A58: FW.8A | B58: 25MM THICK BOARD | C58: M2 | D58: =[1]SUMMARY!E57 -> 5.1 | E58: 1300 | F58: =D58*E58 -> 6630 | H58: =G58*E58 -> 0
A59: FW.9 | B59: SEALENT FOR EXPANSION JOINT | D59: 0 | F59: =D59*E59 -> 0 | H59: =G59*E59 -> 0
A60: FW.9A | B60: GROOVE SIZE 25MM X 25MM DEEP | C60: M | D60: =[1]SUMMARY!E59 -> 34 | E60: 550 | F60: =D60*E60 -> 18700 | H60: =G60*E60 -> 0
D61: 0 | F61: =D61*E61 -> 0 | H61: =G61*E61 -> 0
A62: RF | B62: REINFORCEMENT | D62: 0 | F62: =D62*E62 -> 0 | H62: =G62*E62 -> 0
A63: RF.3 | B63: HIGH STRENGTH DEFORMED BARS MINIMUM Fe-500D N/MM2 | C63: MT | D63: =[1]SUMMARY!E60 -> 10.3375 | E63: 85000 | F63: =D63*E63 -> 878687.5 | G63: =Steel!M266 -> 18.901872 | H63: =G63*E63 -> 1606659.1
D64: 0 | F64: =D64*E64 -> 0 | H64: =G64*E64 -> 0
H65: =G65*E65 -> 0
A66: STL | B66: STRUCTURAL STEEL WORK | D66: 0 | F66: =D66*E66 -> 0 | H66: =G66*E66 -> 0
A67: STL.1 | B67: STRUCTURAL STEEL WORK INCLUDING ONE COAT ZINC CHROMATE PRIMER AND TWO COATS OF ENAMEL PAINT | C67: MT | D67: =[1]SUMMARY!E62 -> 0 | F67: =D67*E67 -> 0 | H67: =G67*E67 -> 0
A68: STL.2 | B68: STEEL INSERTS | C68: KG | D68: =[1]SUMMARY!E63 -> 50 | E68: 175 | F68: =D68*E68 -> 8750 | H68: =G68*E68 -> 0
A69: STL.2C | B69: SAME AS ITEM STL.2 BUT USING ANGLES, CHANNELS AND OTHERS | C69: KG | D69: 0 | F69: =D69*E69 -> 0 | H69: =G69*E69 -> 0
A70: STL.3 | B70: FIXING HOLDING DOWN BOLTS (BOLTS SUPPL BY PEB) | D70: 0 | F70: =D70*E70 -> 0 | H70: =G70*E70 -> 0
A71: STL.3A | B71: 16MM DIA 450 LONG | C71: NO | D71: =[1]SUMMARY!E66 -> 0 | F71: =D71*E71 -> 0 | H71: =G71*E71 -> 0
A72: STL.3B | B72: 20MM DIA 800 LONG | C72: NO | D72: =[1]SUMMARY!E67 -> 0 | F72: =D72*E72 -> 0 | H72: =G72*E72 -> 0
A73: STL.3D | B73: 25MM DIA 1000 LONG | C73: NO | D73: =[1]SUMMARY!E69 -> 0 | F73: =D73*E73 -> 0 | H73: =G73*E73 -> 0
A74: STL.4 | B74: SUPPLYING AND FIXING DOWN BOLTS WITH SLEEVE | C74: KG | D74: =[1]SUMMARY!E71 -> 1.03 | E74: 250 | F74: =D74*E74 -> 257.5 | H74: =G74*E74 -> 0
A75: STL.8 | B75: WICKET GATE | C75: KG | D75: 0 | F75: =D75*E75 -> 0 | H75: =G75*E75 -> 0
A76: STL.10 | B76: AS PER STL.1 BUT WITH TUBULAR SECTION | C76: MT | D76: =[1]SUMMARY!E72 -> 0 | F76: =D76*E76 -> 0 | H76: =G76*E76 -> 0
A77: STL.11 | B77: AS PER STL.1 BUT WITH COLD ROLLED SECTION | C77: MT | D77: =[1]SUMMARY!E74 -> 0 | F77: =D77*E77 -> 0 | H77: =G77*E77 -> 0
A78: STL.19 | B78: M.S.RAILING | D78: 0 | F78: =D78*E78 -> 0 | H78: =G78*E78 -> 0
A79: STL.19B | B79: USING SQUARE/RECTANGULAR/ CIRCULAR HOLLOW PIPES | C79: KG | D79: 0 | F79: =D79*E79 -> 0 | H79: =G79*E79 -> 0
A80: STL.20 | B80: SS RAILING AS PER DESCRIPTION | C80: RMT | D80: =[1]SUMMARY!E75 -> 16.9 | E80: 7500 | F80: =D80*E80 -> 126750 | H80: =G80*E80 -> 0
A81: STL.26 | B81: WALL MOUNTED HAND RAILING | C81: RMT | D81: =[1]SUMMARY!E76 -> 1.03 | E81: 5000 | F81: =D81*E81 -> 5150 | H81: =G81*E81 -> 0
A82: STL.37 | B82: ANCHOR FASTNER BOLT HILTI OR EQUIVALENT | D82: 0 | F82: =D82*E82 -> 0 | H82: =G82*E82 -> 0
A83: STL.37A | B83: 12MM DIA. | C83: NO | D83: =[1]SUMMARY!E78 -> 1.03 | E83: 450 | F83: =D83*E83 -> 463.5 | H83: =G83*E83 -> 0
A84: STL.37B | B84: 16MM DIA. | C84: NO | D84: =[1]SUMMARY!E79 -> 1.03 | E84: 650 | F84: =D84*E84 -> 669.5 | H84: =G84*E84 -> 0
A85: STL.37C | B85: 20MM DIA. | C85: NO | D85: =[1]SUMMARY!E80 -> 1.03 | E85: 700 | F85: =D85*E85 -> 721 | H85: =G85*E85 -> 0
A86: STL.38 | B86: CHEMICAL REBAR HILTI OR EQUIVALENT | D86: 0 | F86: =D86*E86 -> 0 | H86: =G86*E86 -> 0
A87: STL.38B | B87: 10MM DIA REBAR 14MM DIA HOLE,200MM DEEP | C87: NO | D87: =[1]SUMMARY!E83 -> 1.03 | E87: 850 | F87: =D87*E87 -> 875.5 | H87: =G87*E87 -> 0
A88: STL.38C | B88: 12MM DIA REBAR 16MM DIA HOLE,240MM DEEP | C88: NO | D88: =[1]SUMMARY!E84 -> 1.03 | E88: 1100 | F88: =D88*E88 -> 1133 | H88: =G88*E88 -> 0
A89: STL.38D | B89: 16MM DIA REBAR 22MM DIA HOLE,320MM DEEP | C89: NO | D89: =[1]SUMMARY!E85 -> 1.03 | E89: 1500 | F89: =D89*E89 -> 1545 | H89: =G89*E89 -> 0
D90: 0 | F90: =D90*E90 -> 0 | H90: =G90*E90 -> 0
A91: WAL | B91: BRICK MASONRY | D91: 0 | F91: =D91*E91 -> 0 | H91: =G91*E91 -> 0
A92: WAL.1 | B92: BRICK MASONRY IN 1:6 CEMENT MORTAR | D92: 0 | F92: =D92*E92 -> 0 | H92: =G92*E92 -> 0
A93: WAL.1B | B93: PLINTH TO 4.5M | C93: M3 | D93: =[1]SUMMARY!E88 -> 0.8096 | E93: 8000 | F93: =D93*E93 -> 6476.8 | H93: =G93*E93 -> 0
A94: WAL.1C | B94: AT 4.5M TO 9.0M HEIGHT ABOVE PLINTH | C94: M3 | D94: 0 | F94: =D94*E94 -> 0 | H94: =G94*E94 -> 0
A95: WAL.2 | B95: SAME AS ITEM WAL.1 FOR 1:4 CEMENT MORTAR BRICK MASONRY | D95: 0 | F95: =D95*E95 -> 0 | H95: =G95*E95 -> 0
A96: WAL.2A | B96: AT AND BELOW PLINTH | C96: M3 | D96: =[1]SUMMARY!E90 -> 36.235036 | E96: 8500 | F96: =D96*E96 -> 307997.81 | H96: =G96*E96 -> 0
A97: WAL.13 | B97: AUTOCLAVED AERATED CONCRETE BLOCK MASONARY | F97: =D97*E97 -> 0 | H97: =G97*E97 -> 0
A98: WAL.13B | B98: PLINTH TO 4.5M | C98: M3 | D98: =[1]SUMMARY!E93 -> 70.388 | E98: 8500 | F98: =D98*E98 -> 598298 | H98: =G98*E98 -> 0
A99: WAL.13C | B99: AT 4.5M TO 9.0M HEIGHT ABOVE PLINTH | C99: M3 | D99: =[1]SUMMARY!E94 -> 0 | F99: =D99*E99 -> 0 | H99: =G99*E99 -> 0
A100: WAL.13F | B100: HALF PARTATION WALL AERATED BLOCK | C100: M2 | D100: =[1]SUMMARY!E97 -> 1 | E100: 1250 | F100: =D100*E100 -> 1250 | H100: =G100*E100 -> 0
A101: WAL.51 | B101: DISMANTLING BRICK WORK | C101: M3 | D101: =[1]SUMMARY!E98 -> 1.03 | E101: 2800 | F101: =D101*E101 -> 2884 | H101: =G101*E101 -> 0
...

Sheet Excavation
A1: EXC1A : FOOTINGS EXCAVATION QUANTITY FOR DEPTH 0 M TO 1.5 M
A2: S.NO | B2: DESCRIPTION | C2: NO'S | D2: NGL | E2: EXISITING LEVEL | F2: EXCAVATION DEPTH | G2: Length (Mt) | H2: Width (Mt) | I2: Depth (Mt) | J2: QUANTITY CUM
A3: 1 | B3: F1 | C3: 2 | D3: 102.715 | E3: 99.9 | F3: =D3-E3 -> 2.815 | G3: 3.4 | H3: 3 | I3: 1.5 | J3: =I3*H3*G3*C3 -> 30.6
A4: 2 | B4: F2 | C4: 3 | D4: 102.715 | E4: 99.9 | F4: =D4-E4 -> 2.815 | G4: 4.2 | H4: 3.4 | I4: 1.5 | J4: =I4*H4*G4*C4 -> 64.26
A5: 3 | B5: F3 | C5: 1 | D5: 102.715 | E5: 99.9 | F5: =D5-E5 -> 2.815 | G5: 1.4 | H5: 1.4 | I5: 1.5 | J5: =I5*H5*G5*C5 -> 2.94
A6: 4 | B6: F4 | C6: 3 | D6: 102.715 | E6: 99.9 | F6: =D6-E6 -> 2.815 | G6: 2.1 | H6: 2.1 | I6: 1.5 | J6: =I6*H6*G6*C6 -> 19.845
A7: 5 | B7: F6 | C7: 2 | D7: 102.715 | E7: 99.9 | F7: =D7-E7 -> 2.815 | G7: 6.1 | H7: 2.575 | I7: 1.5 | J7: =I7*H7*G7*C7 -> 47.1225
A8: 6 | B8: F9 | C8: 1 | D8: 102.715 | E8: 99.9 | F8: =D8-E8 -> 2.815 | G8: 3.4 | H8: 2.263 | I8: 1.5 | J8: =I8*H8*G8*C8 -> 11.5413
A9: 7 | B9: RF1 | C9: 1 | D9: 102.715 | E9: 99.9 | F9: =D9-E9 -> 2.815 | G9: 27.2 | H9: 4.3 | I9: 1.5 | J9: =I9*H9*G9*C9 -> 175.44
H10: TOTAL | J10: =SUM(J3:J9) -> 351.7488
A11: EXC.1B: FOOTINGS EXCAVATION QUANTITY FOR DEPTH 1.5M TO 3M
A12: S.NO | B12: FOOTONG | C12: NO'S | D12: NGL | E12: EXISITING LEVEL | F12: EXCAVATION DEPTH | G12: Length (Mt) | H12: Width (Mt) | I12: Depth (Mt) | J12: QUANTITY CUM
A13: 1 | B13: F1 | C13: 2 | D13: 102.715 | E13: 99.9 | F13: =D13-E13 -> 2.815 | G13: 3.4 | H13: 3 | I13: =F13-1.5 -> 1.315 | J13: =I13*H13*G13*C13 -> 26.826
A14: 2 | B14: F2 | C14: 3 | D14: 102.715 | E14: 99.9 | F14: =D14-E14 -> 2.815 | G14: 4.2 | H14: 3.4 | I14: =F14-1.5 -> 1.315 | J14: =I14*H14*G14*C14 -> 56.3346
A15: 3 | B15: F3 | C15: 1 | D15: 102.715 | E15: 99.9 | F15: =D15-E15 -> 2.815 | G15: 1.4 | H15: 1.4 | I15: =F15-1.5 -> 1.315 | J15: =I15*H15*G15*C15 -> 2.5774
A16: 4 | B16: F4 | C16: 3 | D16: 102.715 | E16: 99.9 | F16: =D16-E16 -> 2.815 | G16: 2.1 | H16: 2.1 | I16: =F16-1.5 -> 1.315 | J16: =I16*H16*G16*C16 -> 17.39745
A17: 5 | B17: F6 | C17: 2 | D17: 102.715 | E17: 99.9 | F17: =D17-E17 -> 2.815 | G17: 6.1 | H17: 2.575 | I17: =F17-1.5 -> 1.315 | J17: =I17*H17*G17*C17 -> 41.310725
A18: 6 | B18: F9 | C18: 1 | D18: 102.715 | E18: 99.9 | F18: =D18-E18 -> 2.815 | G18: 3.4 | H18: 2.263 | I18: =F18-1.5 -> 1.315 | J18: =I18*H18*G18*C18 -> 10.117873
A19: 7 | B19: RF1 | C19: 1 | D19: 102.715 | E19: 99.9 | F19: =D19-E19 -> 2.815 | G19: 27.2 | H19: 4.3 | I19: =F19-1.5 -> 1.315 | J19: =I19*H19*G19*C19 -> 153.8024
H20: TOTAL | J20: =SUM(J13:J19) -> 308.36645

Sheet Pcc & Rcc
A1: CON.1B: PCC QUANTITY M10
A2: S.NO | B2: DESCRIPTION | C2: NO'S | D2: Length (Mt) | E2: Width (Mt) | F2: Depth (Mt) | G2: QUANTITY CUM
A3: 1 | B3: F1 | C3: 2 | D3: 3.4 | E3: 3 | F3: 0.1 | G3: =F3*E3*D3*C3 -> 2.04
A4: 2 | B4: F2 | C4: 3 | D4: 4.2 | E4: 3.4 | F4: 0.1 | G4: =F4*E4*D4*C4 -> 4.284
A5: 3 | B5: F3 | C5: 1 | D5: 1.4 | E5: 1.4 | F5: 0.1 | G5: =F5*E5*D5*C5 -> 0.196
A6: 4 | B6: F4 | C6: 3 | D6: 2.1 | E6: 2.1 | F6: 0.1 | G6: =F6*E6*D6*C6 -> 1.323
A7: 5 | B7: F6 | C7: 3 | D7: 3.1 | E7: 2.75 | F7: 0.1 | G7: =F7*E7*D7*C7 -> 2.5575
A8: 6 | B8: F9 | C8: 1 | D8: 3.4 | E8: 2.263 | F8: 0.1 | G8: =F8*E8*D8*C8 -> 0.76942
A9: 7 | B9: RF1 | C9: 1 | D9: 27.2 | E9: 4.3 | F9: 0.1 | G9: =F9*E9*D9*C9 -> 11.696
A10: 1 | B10: PB1 | C10: 1 | D10: 5.2 | E10: 0.45 | F10: 0.1 | G10: =F10*E10*D10*C10 -> 0.234
A11: =A10+1 -> 2 | B11: PB1 | C11: 1 | D11: 5.65 | E11: 0.45 | F11: 0.1 | G11: =F11*E11*D11*C11 -> 0.25425
A12: =A11+1 -> 3 | B12: PB1 | C12: 1 | D12: 5.4 | E12: 0.45 | F12: 0.1 | G12: =F12*E12*D12*C12 -> 0.243
A13: =A12+1 -> 4 | B13: PB1 | C13: 1 | D13: 5.45 | E13: 0.45 | F13: 0.1 | G13: =F13*E13*D13*C13 -> 0.24525
A14: =A13+1 -> 5 | B14: PB2 | C14: 1 | D14: 5.2 | E14: 0.45 | F14: 0.1 | G14: =F14*E14*D14*C14 -> 0.234
A15: =A14+1 -> 6 | B15: PB2 | C15: 1 | D15: 5.65 | E15: 0.45 | F15: 0.1 | G15: =F15*E15*D15*C15 -> 0.25425
A16: =A15+1 -> 7 | B16: PB2 | C16: 1 | D16: 5.4 | E16: 0.45 | F16: 0.1 | G16: =F16*E16*D16*C16 -> 0.243
A17: =A16+1 -> 8 | B17: PB2 | C17: 1 | D17: 5.45 | E17: 0.45 | F17: 0.1 | G17: =F17*E17*D17*C17 -> 0.24525
A18: =A17+1 -> 9 | B18: PB3 | C18: 2 | D18: 3.425 | E18: 0.45 | F18: 0.1 | G18: =F18*E18*D18*C18 -> 0.30825
A19: =A18+1 -> 10 | B19: PB3 | C19: 2 | D19: 2.9 | E19: 0.45 | F19: 0.1 | G19: =F19*E19*D19*C19 -> 0.261
A20: =A19+1 -> 11 | B20: PB3 | C20: 2 | D20: 5.375 | E20: 0.45 | F20: 0.1 | G20: =F20*E20*D20*C20 -> 0.48375
A21: =A20+1 -> 12 | B21: PB3 | C21: 2 | D21: 2.2 | E21: 0.45 | F21: 0.1 | G21: =F21*E21*D21*C21 -> 0.198
A22: =A21+1 -> 13 | B22: PB3 | C22: 2 | D22: 2.825 | E22: 0.45 | F22: 0.1 | G22: =F22*E22*D22*C22 -> 0.25425
... A28: =A27+1 -> 19 | B28: PB5 | C28: 1 | D28: 2.375 | E28: 0.45 | F28: 0.1 | G28: =F28*E28*D28*C28 -> 0.106875
E30: TOTAL | G30: =SUM(G3:G28) -> 28.44829
A31: CON.3A,CON.5A: FOOTING RCC QUANTITY M25
A32: S.NO | B32: DESCRIPTION | C32: NO'S | D32: Length (Mt) | E32: Width (Mt) | F32: Depth (Mt) | G32: QUANTITY CUM
B33: Footings
A34: 1 | B34: F1 | C34: 2 | D34: 2.8 | E34: 3.2 | F34: 0.6 | G34: =F34*E34*D34*C34 -> 10.752
A35: =A34+1 -> 2 | B35: F2 | C35: 3 | D35: 3.2 | E35: 4 | F35: 0.75 | G35: =F35*E35*D35*C35 -> 28.8
A36: =A35+1 -> 3 | B36: F3 | C36: 1 | D36: 1.2 | E36: 1.2 | F36: 0.45 | G36: =F36*E36*D36*C36 -> 0.648
A37: =A36+1 -> 4 | B37: F4 | C37: 3 | D37: 1.9 | E37: 1.9 | F37: 0.45 | G37: =F37*E37*D37*C37 -> 4.8735
A38: =A37+1 -> 5 | B38: F6 | C38: 3 | D38: 2.9 | E38: 2.55 | F38: 0.6 | G38: =F38*E38*D38*C38 -> 13.311
A39: =A38+1 -> 6 | B39: F9 | C39: 1 | D39: 2 | E39: 3.2 | F39: 0.45 | G39: =F39*E39*D39*C39 -> 2.88
A40: =A39+1 -> 7 | B40: RF1 | C40: 1 | D40: 4.1 | E40: 27 | F40: 0.6 | G40: =F40*E40*D40*C40 -> 66.42
B41: Pedastals
A42: =A40+1 -> 8 | B42: P1 | C42: 2 | D42: 0.9 | E42: 0.5 | F42: =1.93 -> 1.93 | G42: =F42*E42*D42*C42 -> 1.737 | I42: =I40+1 -> 1 | J42: P1 | K42: 2 | L42: 0.9 | M42: 0.5 | N42: 0.75 | O42: =N42*M42*L42*K42 -> 0.675
A43: =A42+1 -> 9 | B43: P1 | C43: 2 | D43: 0.9 | E43: 0.5 | F43: =1.93 -> 1.93 | G43: =F43*E43*D43*C43 -> 1.737 | I43: =I42+1 -> 2 | J43: P1 | K43: 2 | L43: 0.9 | M43: 0.5 | N43: 0.75 | O43: =N43*M43*L43*K43 -> 0.675
A44: =A43+1 -> 10 | B44: P2 | C44: 1 | D44: 0.55 | E44: 0.55 | F44: =1.93 -> 1.93 | G44: =F44*E44*D44*C44 -> 0.583825 | I44: =I43+1 -> 3 | J44: P2 | K44: 1 | L44: 0.55 | M44: 0.55 | N44: 0.6 | O44: =N44*M44*L44*K44 -> 0.1815
A45: =A44+1 -> 11 | B45: P2 | C45: 1 | D45: 0.55 | E45: 0.55 | F45: =2.08 -> 2.08 | G45: =F45*E45*D45*C45 -> 0.6292 | I45: =I44+1 -> 4 | J45: P2 | K45: 1 | L45: 0.55 | M45: 0.55 | N45: 0.6 | O45: =N45*M45*L45*K45 -> 0.1815
A46: =A45+1 -> 12 | B46: P3 | C46: 1 | D46: 0.65 | E46: 0.65 | F46: =1.93 -> 1.93 | G46: =F46*E46*D46*C46 -> 0.815425 | I46: =I45+1 -> 5 | J46: P3 | K46: 1 | L46: 0.65 | M46: 0.65 | N46: 0.6 | O46: =N46*M46*L46*K46 -> 0.2535
A47: =A46+1 -> 13 | B47: P3 | C47: 1 | D47: 0.65 | E47: 0.65 | F47: =1.93 -> 1.93 | G47: =F47*E47*D47*C47 -> 0.815425 | I47: =I46+1 -> 6 | J47: P3 | K47: 1 | L47: 0.65 | M47: 0.65 | N47: 0.6 | O47: =N47*M47*L47*K47 -> 0.2535
A48: =A47+1 -> 14 | B48: P4 | C48: 1 | D48: 0.8 | E48: 0.8 | F48: =1.93 -> 1.93 | G48: =F48*E48*D48*C48 -> 1.2352 | I48: =I47+1 -> 7 | J48: P4 | K48: 1 | L48: 0.8 | M48: 0.8 | N48: 0.6 | O48: =N48*M48*L48*K48 -> 0.384
A49: =A48+1 -> 15 | B49: P4 | C49: 1 | D49: 0.8 | E49: 0.8 | F49: =1.93 -> 1.93 | G49: =F49*E49*D49*C49 -> 1.2352 | I49: =I48+1 -> 8 | J49: P4 | K49: 1 | L49: 0.8 | M49: 0.8 | N49: 0.6 | O49: =N49*M49*L49*K49 -> 0.384
A50: =A49+1 -> 16 | B50: P5 | C50: 1 | D50: 0.8 | E50: 0.8 | F50: =1.93 -> 1.93 | G50: =F50*E50*D50*C50 -> 1.2352 | I50: =I49+1 -> 9 | J50: P5 | K50: 1 | L50: 0.8 | M50: 0.8 | N50: 0.6 | O50: =N50*M50*L50*K50 -> 0.384
A51: =A50+1 -> 17 | B51: P5 | C51: 1 | D51: 0.8 | E51: 0.8 | F51: =1.93 -> 1.93 | G51: =F51*E51*D51*C51 -> 1.2352 | I51: =I50+1 -> 10 | J51: P5 | K51: 1 | L51: 0.8 | M51: 0.8 | N51: 0.6 | O51: =N51*M51*L51*K51 -> 0.384
A52: =A51+1 -> 18 | B52: P6 | C52: 1 | D52: 0.55 | E52: 0.55 | F52: =1.93 -> 1.93 | G52: =F52*E52*D52*C52 -> 0.583825 | I52: =I51+1 -> 11 | J52: P6 | K52: 1 | L52: 0.55 | M52: 0.55 | N52: 0.6 | O52: =N52*M52*L52*K52 -> 0.1815
A53: =A52+1 -> 19 | B53: P6 | C53: 1 | D53: 0.55 | E53: 0.55 | F53: =1.93 -> 1.93 | G53: =F53*E53*D53*C53 -> 0.583825 | I53: =I52+1 -> 12 | J53: P6 | K53: 1 | L53: 0.55 | M53: 0.55 | N53: 0.6 | O53: =N53*M53*L53*K53 -> 0.1815
A54: =A53+1 -> 20 | B54: P7 | C54: 3 | D54: 1 | E54: 0.6 | F54: =1.93 -> 1.93 | G54: =F54*E54*D54*C54 -> 3.474 | I54: =I53+1 -> 13 | J54: P7 | K54: 3 | L54: 1 | M54: 0.6 | N54: 0.6 | O54: =N54*M54*L54*K54 -> 1.08
A55: =A54+1 -> 21 | B55: P7 | C55: 2 | D55: 1 | E55: 0.6 | F55: =1.78 -> 1.78 | G55: =F55*E55*D55*C55 -> 2.136 | I55: =I54+1 -> 14 | J55: P7 | K55: 2 | L55: 1 | M55: 0.6 | N55: 0.6 | O55: =N55*M55*L55*K55 -> 0.72
A56: =A55+1 -> 22 | B56: P8 | C56: 1 | D56: 0.45 | E56: 0.45 | F56: 2.08 | G56: =F56*E56*D56*C56 -> 0.4212 | I56: =I55+1 -> 15 | J56: P8 | K56: 1 | L56: 0.45 | M56: 0.45 | N56: 0.6 | O56: =N56*M56*L56*K56 -> 0.1215
A57: =A56+1 -> 23 | B57: P7a | C57: 1 | D57: 0.6 | E57: 1.025 | F57: 1.78 | G57: =F57*E57*D57*C57 -> 1.0947 | I57: =I56+1 -> 16 | J57: P7a | K57: 1 | L57: 0.6 | M57: 1.025 | N57: 0.6 | O57: =N57*M57*L57*K57 -> 0.369
A58: =A57+1 -> 24 | B58: P8a | C58: 1 | D58: 0.45 | E58: 0.45 | F58: 1.78 | G58: =F58*E58*D58*C58 -> 0.36045 | I58: =I57+1 -> 17 | J58: P8a | K58: 1 | L58: 0.45 | M58: 0.45 | N58: 0.6 | O58: =N58*M58*L58*K58 -> 0.1215
A59: =A58+1 -> 25 | B59: C1 | C59: 1 | D59: 0.6 | E59: 0.6 | F59: 2.08 | G59: =F59*E59*D59*C59 -> 0.7488 | I59: =I58+1 -> 18 | J59: C1 | K59: 1 | L59: 0.6 | M59: 0.6 | N59: 0.6 | O59: =N59*M59*L59*K59 -> 0.216
A60: =A59+1 -> 26 | B60: C1 | C60: 1 | D60: 0.6 | E60: 0.6 | F60: 1.93 | G60: =F60*E60*D60*C60 -> 0.6948 | I60: =I59+1 -> 19 | J60: C1 | K60: 1 | L60: 0.6 | M60: 0.6 | N60: 0.6 | O60: =N60*M60*L60*K60 -> 0.216
A61: =A60+1 -> 27 | B61: C2 | C61: 1 | D61: 0.45 | E61: 0.45 | F61: 2.08 | G61: =F61*E61*D61*C61 -> 0.4212 | I61: =I60+1 -> 20 | J61: C2 | K61: 1 | L61: 0.45 | M61: 0.45 | N61: 0.6 | O61: =N61*M61*L61*K61 -> 0.1215
G62: =SUM(G34:G61) -> 149.46197 | O62: =SUM(O42:O61) -> 7.0845
A63: CON.3B,CON.5A: PLINTH RCC QUANTITY M25
A64: S.NO | B64: DESCRIPTION | C64: NO'S | D64: Length (Mt) | E64: Width (Mt) | F64: Depth (Mt) | G64: QUANTITY CUM
A65: =A61+1 -> 28 | B65: Plinth Beam
A66: =A65+1 -> 29 | B66: PB1 | C66: 1 | D66: 5.2 | E66: 0.3 | F66: 0.6 | G66: =F66*E66*D66*C66 -> 0.936
A67: =A66+1 -> 30 | B67: PB1 | C67: 1 | D67: 5.65 | E67: 0.3 | F67: 0.6 | G67: =F67*E67*D67*C67 -> 1.017
A68: =A67+1 -> 31 | B68: PB1 | C68: 1 | D68: 5.4 | E68: 0.3 | F68: 0.6 | G68: =F68*E68*D68*C68 -> 0.972
A69: =A68+1 -> 32 | B69: PB1 | C69: 1 | D69: 5.45 | E69: 0.3 | F69: 0.6 | G69: =F69*E69*D69*C69 -> 0.981
A70: =A69+1 -> 33 | B70: PB2 | C70: 1 | D70: 5.2 | E70: 0.3 | F70: 0.6 | G70: =F70*E70*D70*C70 -> 0.936
A71: =A70+1 -> 34 | B71: PB2 | C71: 1 | D71: 5.65 | E71: 0.3 | F71: 0.6 | G71: =F71*E71*D71*C71 -> 1.017
A72: =A71+1 -> 35 | B72: PB2 | C72: 1 | D72: 5.4 | E72: 0.3 | F72: 0.6 | G72: =F72*E72*D72*C72 -> 0.972
A73: =A72+1 -> 36 | B73: PB2 | C73: 1 | D73: 5.45 | E73: 0.3 | F73: 0.6 | G73: =F73*E73*D73*C73 -> 0.981
A74: =A73+1 -> 37 | B74: PB3 | C74: 2 | D74: 3.425 | E74: 0.3 | F74: 0.6 | G74: =F74*E74*D74*C74 -> 1.233
A75: =A74+1 -> 38 | B75: PB3 | C75: 2 | D75: 2.9 | E75: 0.3 | F75: 0.6 | G75: =F75*E75*D75*C75 -> 1.044
A76: =A75+1 -> 39 | B76: PB3 | C76: 2 | D76: 5.375 | E76: 0.3 | F76: 0.6 | G76: =F76*E76*D76*C76 -> 1.935
A77: =A76+1 -> 40 | B77: PB3 | C77: 2 | D77: 2.2 | E77: 0.3 | F77: 0.6 | G77: =F77*E77*D77*C77 -> 0.792
... A84: =A83+1 -> 47 | B84: PB4 | C84: 2 | D84: 10.9 | E84: 0.25 | F84: 0.2 | G84: =F84*E84*D84*C84 -> 1.09
A85: =A83+1 -> 47 | B85: PB5 | C85: 1 | D85: 2.375 | E85: 0.3 | F85: 0.6 | G85: =F85*E85*D85*C85 -> 0.4275
E87: TOTAL | G87: =SUM(G66:G86) -> 25.19398

Sheet Shuttering
A1: FW.1A: FOOTING SHUTTERING QUANTITY BELOW PLINTH
A2: S.NO | B2: DESCRIPTION | C2: NO'S | D2: Length (Mt) | E2: Width (Mt) | F2: Depth (Mt) | G2: QUANTITY Sqm
A3: 1 | B3: F1 | C3: 2 | D3: 2.8 | E3: 3.2 | F3: 0.6 | G3: =(D3+E3)*2*F3*C3 -> 14.4
A4: 2 | B4: F2 | C4: 3 | D4: 3.2 | E4: 4 | F4: 0.75 | G4: =(D4+E4)*2*F4*C4 -> 32.4
A5: 3 | B5: F3 | C5: 1 | D5: 1.2 | E5: 1.2 | F5: 0.45 | G5: =(D5+E5)*2*F5*C5 -> 2.16
A6: 4 | B6: F4 | C6: 3 | D6: 1.9 | E6: 1.9 | F6: 0.45 | G6: =(D6+E6)*2*F6*C6 -> 10.26
A7: 5 | B7: F6 | C7: 3 | D7: 2.9 | E7: 2.55 | F7: 0.6 | G7: =(D7+E7)*2*F7*C7 -> 19.62
A8: 6 | B8: F9 | C8: 1 | D8: 2 | E8: 3.2 | F8: 0.45 | G8: =(D8+E8)*2*F8*C8 -> 4.68
A9: 7 | B9: RF1 | C9: 1 | D9: 4.1 | E9: 27 | F9: 0.6 | G9: =(D9+E9)*2*F9*C9 -> 37.32
E10: TOTAL | G10: =SUM(G3:G9) -> 120.84
A12: S.NO | B12: DESCRIPTION | C12: NO'S | D12: Length (Mt) | E12: Width (Mt) | F12: Depth (Mt) | G12: QUANTITY Sqm
A13: 1 | B13: P1 | C13: 2 | D13: 0.9 | E13: 0.5 | F13: =1.93 -> 1.93 | G13: =(D13+E13)*2*F13*C13 -> 10.808
A14: =A13+1 -> 2 | B14: P1 | C14: 2 | D14: 0.9 | E14: 0.5 | F14: =1.93 -> 1.93 | G14: =(D14+E14)*2*F14*C14 -> 10.808
A15: =A14+1 -> 3 | B15: P2 | C15: 1 | D15: 0.55 | E15: 0.55 | F15: =1.93 -> 1.93 | G15: =(D15+E15)*2*F15*C15 -> 4.246
A16: =A15+1 -> 4 | B16: P2 | C16: 1 | D16: 0.55 | E16: 0.55 | F16: 2.08 | G16: =(D16+E16)*2*F16*C16 -> 4.576
A17: =A16+1 -> 5 | B17: P3 | C17: 1 | D17: 0.65 | E17: 0.65 | F17: =1.93 -> 1.93 | G17: =(D17+E17)*2*F17*C17 -> 5.018
A18: =A17+1 -> 6 | B18: P3 | C18: 1 | D18: 0.65 | E18: 0.65 | F18: =1.93 -> 1.93 | G18: =(D18+E18)*2*F18*C18 -> 5.018
A19: =A18+1 -> 7 | B19: P4 | C19: 1 | D19: 0.8 | E19: 0.8 | F19: =1.93 -> 1.93 | G19: =(D19+E19)*2*F19*C19 -> 6.176
A20: =A19+1 -> 8 | B20: P4 | C20: 1 | D20: 0.8 | E20: 0.8 | F20: =1.93 -> 1.93 | G20: =(D20+E20)*2*F20*C20 -> 6.176
A21: =A20+1 -> 9 | B21: P5 | C21: 1 | D21: 0.8 | E21: 0.8 | F21: =1.93 -> 1.93 | G21: =(D21+E21)*2*F21*C21 -> 6.176
A22: =A21+1 -> 10 | B22: P5 | C22: 1 | D22: 0.8 | E22: 0.8 | F22: =1.93 -> 1.93 | G22: =(D22+E22)*2*F22*C22 -> 6.176
A23: =A22+1 -> 11 | B23: P6 | C23: 1 | D23: 0.55 | E23: 0.55 | F23: =1.93 -> 1.93 | G23: =(D23+E23)*2*F23*C23 -> 4.246
A24: =A23+1 -> 12 | B24: P6 | C24: 1 | D24: 0.55 | E24: 0.55 | F24: =1.93 -> 1.93 | G24: =(D24+E24)*2*F24*C24 -> 4.246
A25: =A24+1 -> 13 | B25: P7 | C25: 3 | D25: 1 | E25: 0.6 | F25: =1.93 -> 1.93 | G25: =(D25+E25)*2*F25*C25 -> 18.528
A26: =A25+1 -> 14 | B26: P7 | C26: 2 | D26: 1 | E26: 0.6 | F26: =1.78 -> 1.78 | G26: =(D26+E26)*2*F26*C26 -> 11.392
A27: =A26+1 -> 15 | B27: P8 | C27: 1 | D27: 0.45 | E27: 0.45 | F27: 2.08 | G27: =(D27+E27)*2*F27*C27 -> 3.744
A28: =A27+1 -> 16 | B28: P7a/P8a | C28: 1 | E28: =1.025+0.45+0.325+0.575+0.6+0.925 -> 3.9 | F28: 1.78 | G28: =(D28+E28)*F28*C28 -> 6.942
A29: =A28+1 -> 17 | B29: C1 | C29: 1 | D29: 0.6 | E29: 0.6 | F29: 2.08 | G29: =(D29+E29)*2*F29*C29 -> 4.992
A30: =A29+1 -> 18 | B30: C1 | C30: 1 | D30: 0.6 | E30: 0.6 | F30: 1.93 | G30: =(D30+E30)*2*F30*C30 -> 4.632
A31: =A30+1 -> 19 | B31: C2 | C31: 1 | D31: 0.45 | E31: 0.45 | F31: 2.08 | G31: =(D31+E31)*2*F31*C31 -> 3.744
E32: TOTAL | G32: =SUM(G13:G31) -> 127.644
A34: FW.1B: FOOTING SHUTTERING QUANTITY PLINTH TO 4.5 M
A35: S.NO | B35: DESCRIPTION | C35: NO'S | D35: Length (Mt) | E35: No.of sides | F35: Depth (Mt) | G35: QUANTITY Sqm
B36: Plinth Beam
A37: 1 | B37: PB1 | C37: 1 | D37: 5.2 | E37: 2 | F37: 0.6 | G37: =F37*D37*C37*E37 -> 6.24
A38: =A37+1 -> 2 | B38: PB1 | C38: 1 | D38: 5.65 | E38: 2 | F38: 0.6 | G38: =F38*D38*C38*E38 -> 6.78
A39: =A38+1 -> 3 | B39: PB1 | C39: 1 | D39: 5.4 | E39: 2 | F39: 0.6 | G39: =F39*D39*C39*E39 -> 6.48
A40: =A39+1 -> 4 | B40: PB1 | C40: 1 | D40: 5.45 | E40: 2 | F40: 0.6 | G40: =F40*D40*C40*E40 -> 6.54
A41: =A40+1 -> 5 | B41: PB2 | C41: 1 | D41: 5.2 | E41: 2 | F41: 0.6 | G41: =F41*D41*C41*E41 -> 6.24
A42: =A41+1 -> 6 | B42: PB2 | C42: 1 | D42: 5.65 | E42: 2 | F42: 0.6 | G42: =F42*D42*C42*E42 -> 6.78
A43: =A42+1 -> 7 | B43: PB2 | C43: 1 | D43: 5.4 | E43: 2 | F43: 0.6 | G43: =F43*D43*C43*E43 -> 6.48
A44: =A43+1 -> 8 | B44: PB2 | C44: 1 | D44: 5.45 | E44: 2 | F44: 0.6 | G44: =F44*D44*C44*E44 -> 6.54
A45: =A44+1 -> 9 | B45: PB3 | C45: 2 | D45: 3.425 | E45: 2 | F45: 0.6 | G45: =F45*D45*C45*E45 -> 8.22
A46: =A45+1 -> 10 | B46: PB3 | C46: 2 | D46: 2.9 | E46: 2 | F46: 0.6 | G46: =F46*D46*C46*E46 -> 6.96
A47: =A46+1 -> 11 | B47: PB3 | C47: 2 | D47: 5.375 | E47: 2 | F47: 0.6 | G47: =F47*D47*C47*E47 -> 12.9
A48: =A47+1 -> 12 | B48: PB3 | C48: 2 | D48: 2.2 | E48: 2 | F48: 0.6 | G48: =F48*D48*C48*E48 -> 5.28
A49: =A48+1 -> 13 | B49: PB3 | C49: 2 | D49: 2.825 | E49: 2 | F49: 0.6 | G49: =F49*D49*C49*E49 -> 6.78
... A55: =A54+1 -> 19 | B55: PB4 | C55: 2 | D55: 9.1 | E55: 1 | F55: 0.5 | G55: =F55*D55*C55*E55 -> 9.1
A56: =A54+1 -> 19 | B56: PB4 | C56: 2 | D56: 10.9 | E56: 2 | F56: 0.2 | G56: =F56*D56*C56*E56 -> 8.72
A57: =A56+1 -> 20 | B57: PB4 | C57: 2 | D57: 10.9 | E57: 2 | F57: 0.25 | G57: =F57*D57*C57*E57 -> 10.9
A58: =A54+1 -> 19 | B58: PB5 | C58: 1 | D58: 2.375 | E58: 2 | F58: 0.6 | G58: =F58*D58*C58*E58 -> 2.85
E59: TOTAL | G59: =SUM(G37:G58) -> 162.1132

Sheet Steel
A1: FOOTING STEEL
A2: S.NO | B2: Description | C2: NO'S | D2: Direction | F2: Size | G2: Dia | H2: Spacing | I2: No.of Bars | J2: Cutting Length | K2: Total C.L | L2: Unit Wt | M2: Total Wt
A3: 1 | B3: F1 | C3: 2 | D3: Bottom Mat | E3: X-axis | F3: 2.8*3.2 | G3: 10 | H3: 100 | I3: =ROUND(3.1/0.1+1,0) -> 32 | J3: 3.5 | K3: =I3*J3 -> 112 | L3: =G3*G3/162.2 -> 0.61652281 | M3: =(K3*L3*C3) -> 138.10111
C4: 2 | E4: Y-axis | G4: 10 | H4: 100 | I4: =ROUND(2.7/0.1+1,0) -> 28 | J4: 3.9 | K4: =I4*J4 -> 109.2 | L4: =G4*G4/162.2 -> 0.61652281 | M4: =(K4*L4*C4) -> 134.64858
C5: 2 | D5: Top mat | E5: X-axis | F5: 2.8*3.2 | G5: 10 | H5: 100 | I5: =ROUND(3.1/0.1+1,0) -> 32 | J5: 3.5 | K5: =I5*J5 -> 112 | L5: =G5*G5/162.2 -> 0.61652281 | M5: =(K5*L5*C5) -> 138.10111
C6: 2 | E6: Y-axis | G6: 10 | H6: 100 | I6: =ROUND(2.7/0.1+1,0) -> 28 | J6: 3.9 | K6: =I6*J6 -> 109.2 | L6: =G6*G6/162.2 -> 0.61652281 | M6: =(K6*L6*C6) -> 134.64858
A7: 2 | B7: F2 | C7: 3 | D7: Bottom Mat | E7: X-axis | F7: 3.4*4 | G7: 12 | H7: 125 | I7: =ROUND(3.9/0.125+1,0) -> 32 | J7: 4.25 | K7: =I7*J7 -> 136 | L7: =G7*G7/162.2 -> 0.88779285 | M7: =(K7*L7*C7) -> 362.21948
C8: 3 | E8: Y-axis | G8: 12 | H8: 125 | I8: =ROUND(3.3/0.125+1,0) -> 27 | J8: 4.85 | K8: =I8*J8 -> 130.95 | L8: =G8*G8/162.2 -> 0.88779285 | M8: =(K8*L8*C8) -> 348.76942
C9: 3 | D9: Top mat | E9: X-axis | F9: 3.4*4 | G9: 10 | H9: 100 | I9: =ROUND(3.9/0.1+1,0) -> 40 | J9: 4.25 | K9: =I9*J9 -> 170 | L9: =G9*G9/162.2 -> 0.61652281 | M9: =(K9*L9*C9) -> 314.42663
C10: 3 | E10: Y-axis | G10: 10 | H10: 100 | I10: =ROUND(3.3/0.1+1,0) -> 34 | J10: 4.85 | K10: =I10*J10 -> 164.9 | L10: =G10*G10/162.2 -> 0.61652281 | M10: =(K10*L10*C10) -> 304.99383
A11: 3 | B11: F3 | C11: 1 | D11: Bottom Mat | E11: X-axis | F11: 1.2*1.2 | G11: 10 | H11: 150 | I11: =ROUND(1.1/0.15+1,0) -> 8 | J11: 1.75 | K11: =I11*J11 -> 14 | L11: =G11*G11/162.2 -> 0.61652281 | M11: =(K11*L11*C11) -> 8.6313194
C12: 1 | E12: Y-axis | G12: 10 | H12: 150 | I12: =ROUND(1.1/0.15+1,0) -> 8 | J12: 1.75 | K12: =I12*J12 -> 14 | L12: =G12*G12/162.2 -> 0.61652281 | M12: =(K12*L12*C12) -> 8.6313194
C13: 1 | D13: Top mat | E13: X-axis | F13: 1.2*1.2 | G13: 10 | H13: 150 | I13: =ROUND(1.1/0.15+1,0) -> 8 | J13: 1.75 | K13: =I13*J13 -> 14 | L13: =G13*G13/162.2 -> 0.61652281 | M13: =(K13*L13*C13) -> 8.6313194
C14: 1 | E14: Y-axis | G14: 10 | H14: 150 | I14: =ROUND(1.1/0.15+1,0) -> 8 | J14: 1.75 | K14: =I14*J14 -> 14 | L14: =G14*G14/162.2 -> 0.61652281 | M14: =(K14*L14*C14) -> 8.6313194
A15: 4 | B15: F4 | C15: 3 | D15: Bottom Mat | E15: X-axis | F15: 1.9*1.9 | G15: 10 | H15: 125 | I15: =ROUND(1.8/0.125+1,0) -> 15 | J15: 2.45 | K15: =I15*J15 -> 36.75 | L15: =G15*G15/162.2 -> 0.61652281 | M15: =(K15*L15*C15) -> 67.97164
C16: 3 | E16: Y-axis | G16: 10 | H16: 125 | I16: =ROUND(1.8/0.125+1,0) -> 15 | J16: 2.45 | K16: =I16*J16 -> 36.75 | L16: =G16*G16/162.2 -> 0.61652281 | M16: =(K16*L16*C16) -> 67.97164
C17: 3 | D17: Top mat | E17: X-axis | F17: 1.9*1.9 | G17: 10 | H17: 150 | I17: =ROUND(1.8/0.15+1,0) -> 13 | J17: 2.45 | K17: =I17*J17 -> 31.85 | L17: =G17*G17/162.2 -> 0.61652281 | M17: =(K17*L17*C17) -> 58.908755
C18: 3 | E18: Y-axis | G18: 10 | H18: 150 | I18: =ROUND(1.8/0.15+1,0) -> 13 | J18: 2.45 | K18: =I18*J18 -> 31.85 | L18: =G18*G18/162.2 -> 0.61652281 | M18: =(K18*L18*C18) -> 58.908755
A19: 5 | B19: F6 | C19: 3 | D19: Bottom Mat | E19: X-axis | F19: 2.9*2.55 | G19: 10 | H19: 100 | I19: =ROUND(2.8/0.1+1,0) -> 29 | J19: 3.25 | K19: =I19*J19 -> 94.25 | L19: =G19*G19/162.2 -> 0.61652281 | M19: =(K19*L19*C19) -> 174.32182
C20: 3 | E20: Y-axis | G20: 10 | H20: 100 | I20: =ROUND(2.45/0.1+1,0) -> 26 | J20: 3.6 | K20: =I20*J20 -> 93.6 | L20: =G20*G20/162.2 -> 0.61652281 | M20: =(K20*L20*C20) -> 173.11961
C21: 3 | D21: Top mat | E21: X-axis | F21: 2.9*2.550 | G21: 10 | H21: 125 | I21: =ROUND(2.7/0.1+1,0) -> 28 | J21: 3.25 | K21: =I21*J21 -> 91 | L21: =G21*G21/162.2 -> 0.61652281 | M21: =(K21*L21*C21) -> 168.31073
C22: 3 | E22: Y-axis | G22: 10 | H22: 125 | I22: =ROUND(2.45/0.125+1,0) -> 21 | J22: 3.6 | K22: =I22*J22 -> 75.6 | L22: =G22*G22/162.2 -> 0.61652281 | M22: =(K22*L22*C22) -> 139.82737
A23: 6 | B23: F9 | C23: 1 | D23: Bottom Mat | E23: X-axis | F23: 2*3.2 | G23: 10 | H23: 125 | I23: =ROUND(3.1/0.125+1,0) -> 26 | J23: 2.55 | K23: =I23*J23 -> 66.3 | L23: =G23*G23/162.2 -> 0.61652281 | M23: =(K23*L23*C23) -> 40.875462
C24: 1 | E24: Y-axis | G24: 10 | H24: 125 | I24: =ROUND(1.9/0.125+1,0) -> 16 | J24: 3.75 | K24: =I24*J24 -> 60 | L24: =G24*G24/162.2 -> 0.61652281 | M24: =(K24*L24*C24) -> 36.991369
C25: 1 | D25: Top mat | E25: X-axis | F25: 2*3.2 | G25: 10 | H25: 125 | I25: =ROUND(3.1/0.125+1,0) -> 26 | J25: 2.55 | K25: =I25*J25 -> 66.3 | L25: =G25*G25/162.2 -> 0.61652281 | M25: =(K25*L25*C25) -> 40.875462
C26: 1 | E26: Y-axis | G26: 10 | H26: 125 | I26: =ROUND(1.9/0.125+1,0) -> 16 | J26: 3.75 | K26: =I26*J26 -> 60 | L26: =G26*G26/162.2 -> 0.61652281 | M26: =(K26*L26*C26) -> 36.991369
A27: 7 | B27: Shear Keys | C27: 1 | G27: 10 | I27: =24*14 -> 336 | J27: 0.37 | K27: =I27*J27 -> 124.32 | L27: =G27*G27/162.2 -> 0.61652281 | M27: =(K27*L27*C27) -> 76.646116
A28: 8 | B28: RF1 | C28: 1 | D28: Bottom Mat | E28: X-axis | F28: 27*4.1 | G28: 12 | H28: 100 | I28: =ROUND(26.9/0.1+1,0) -> 270 | J28: 4.8 | K28: =I28*J28 -> 1296 | L28: =G28*G28/162.2 -> 0.88779285 | M28: =(K28*L28*C28) -> 1150.5795
C29: 1 | E29: Y-axis | G29: 12 | H29: 100 | I29: =ROUND(4/0.1+1,0) -> 41 | J29: 29.5 | K29: =I29*J29 -> 1209.5 | L29: =G29*G29/162.2 -> 0.88779285 | M29: =(K29*L29*C29) -> 1073.7855
C30: 1 | D30: Top mat | E30: X-axis | F30: 27*4.1 | G30: 12 | H30: 100 | I30: =ROUND(26.9/0.1+1,0) -> 270 | J30: 4.8 | K30: =I30*J30 -> 1296 | L30: =G30*G30/162.2 -> 0.88779285 | M30: =(K30*L30*C30) -> 1150.5795
C31: 1 | E31: Y-axis | G31: 12 | H31: 100 | I31: =ROUND(4/0.1+1,0) -> 41 | J31: 29.5 | K31: =I31*J31 -> 1209.5 | L31: =G31*G31/162.2 -> 0.88779285 | M31: =(K31*L31*C31) -> 1073.7855
A32: 9 | B32: Chair | C32: 1 | G32: 12 | I32: 79 | J32: 2.6 | K32: =I32*J32 -> 205.4 | L32: =G32*G32/162.2 -> 0.88779285 | M32: =(K32*L32*C32) -> 182.35265
A33: PEDASTAL VERTICAL STEEL
A34: 1 | B34: P1 | F34: 0.5*0.9
B35: Main Bar | C35: 4 | G35: 25 | I35: 14 | J35: 3.68 | K35: =I35*J35 -> 51.52 | L35: =G35*G35/162.2 -> 3.8532676 | M35: =(K35*L35*C35) -> 794.08138
B36: Main Bar | C36: 4 | G36: 20 | I36: 10 | J36: 3.68 | K36: =I36*J36 -> 36.8 | L36: =G36*G36/162.2 -> 2.4660912 | M36: =(K36*L36*C36) -> 363.00863
A37: 2 | B37: P2 | F37: 0.55*0.55
B38: Main Bar | C38: 2 | G38: 16 | I38: 8 | J38: 2.78 | K38: =I38*J38 -> 22.24 | L38: =G38*G38/162.2 -> 1.5782984 | M38: =(K38*L38*C38) -> 70.202713
B39: Main Bar | C39: 2 | G39: 12 | I39: 8 | J39: 2.78 | K39: =I39*J39 -> 22.24 | L39: =G39*G39/162.2 -> 0.88779285 | M39: =(K39*L39*C39) -> 39.489026
A40: 3 | B40: P3 | F40: 0.65*0.65
B41: Main Bar | C41: 2 | G41: 20 | I41: 4 | J41: 2.78 | K41: =I41*J41 -> 11.12 | L41: =G41*G41/162.2 -> 2.4660912 | M41: =(K41*L41*C41) -> 54.845869
B42: Main Bar | C42: 2 | G42: 16 | I42: 16 | J42: 2.78 | K42: =I42*J42 -> 44.48 | L42: =G42*G42/162.2 -> 1.5782984 | M42: =(K42*L42*C42) -> 140.40543
A43: 4 | B43: P4 | F43: 0.8*0.8
B44: Main Bar | C44: 2 | G44: 20 | I44: 4 | J44: 2.78 | K44: =I44*J44 -> 11.12 | L44: =G44*G44/162.2 -> 2.4660912 | M44: =(K44*L44*C44) -> 54.845869
B45: Main Bar | C45: 2 | G45: 16 | I45: 24 | J45: 2.78 | K45: =I45*J45 -> 66.72 | L45: =G45*G45/162.2 -> 1.5782984 | M45: =(K45*L45*C45) -> 210.60814
A46: 5 | B46: P5 | F46: 0.8*0.8
B47: Main Bar | C47: 2 | G47: 20 | I47: 4 | J47: 2.78 | K47: =I47*J47 -> 11.12 | L47: =G47*G47/162.2 -> 2.4660912 | M47: =(K47*L47*C47) -> 54.845869
B48: Main Bar | C48: 2 | G48: 16 | I48: 24 | J48: 2.78 | K48: =I48*J48 -> 66.72 | L48: =G48*G48/162.2 -> 1.5782984 | M48: =(K48*L48*C48) -> 210.60814
A49: 6 | B49: P6 | F49: 0.55*0.55
B50: Main Bar | C50: 2 | G50: 16 | I50: 16 | J50: 3.58 | K50: =I50*J50 -> 57.28 | L50: =G50*G50/162.2 -> 1.5782984 | M50: =(K50*L50*C50) -> 180.80986
A51: 7 | B51: P7 | F51: 0.6*1.0
B52: Main Bar | C52: 5 | G52: 25 | I52: 20 | J52: 3.68 | K52: =I52*J52 -> 73.6 | L52: =G52*G52/162.2 -> 3.8532676 | M52: =(K52*L52*C52) -> 1418.0025
B53: Main Bar | C53: 5 | G53: 20 | I53: 8 | J53: 3.68 | K53: =I53*J53 -> 29.44 | L53: =G53*G53/162.2 -> 2.4660912 | M53: =(K53*L53*C53) -> 363.00863
A54: 8 | B54: P8 | F54: 0.45*0.45
B55: Main Bar | C55: 1 | G55: 16 | I55: 4 | J55: 2.78 | K55: =I55*J55 -> 11.12 | L55: =G55*G55/162.2 -> 1.5782984 | M55: =(K55*L55*C55) -> 17.550678
B56: Main Bar | C56: 1 | G56: 12 | I56: 8 | J56: 2.78 | K56: =I56*J56 -> 22.24 | L56: =G56*G56/162.2 -> 0.88779285 | M56: =(K56*L56*C56) -> 19.744513
A57: 9 | B57: C1 | F57: 0.45*0.45
B58: Main Bar | C58: 2 | G58: 20 | I58: 4 | J58: 2.78 | K58: =I58*J58 -> 11.12 | L58: =G58*G58/162.2 -> 2.4660912 | M58: =(K58*L58*C58) -> 54.845869
B59: Main Bar | C59: 2 | G59: 16 | I59: 16 | J59: 2.78 | K59: =I59*J59 -> 44.48 | L59: =G59*G59/162.2 -> 1.5782984 | M59: =(K59*L59*C59) -> 140.40543
A60: 10 | B60: C1 | F60: 0.45*0.45
B61: Main Bar | C61: 2 | G61: 20 | I61: 4 | J61: 2.78 | K61: =I61*J61 -> 11.12 | L61: =G61*G61/162.2 -> 2.4660912 | M61: =(K61*L61*C61) -> 54.845869
B62: Main Bar | C62: 2 | G62: 16 | I62: 4 | J62: 2.78 | K62: =I62*J62 -> 11.12 | L62: =G62*G62/162.2 -> 1.5782984 | M62: =(K62*L62*C62) -> 35.101356
A63: 11 | B63: P7a/P8a | F63: 3.4*3.8
B64: Main Bar | C64: 1 | G64: 25 | I64: 20 | J64: 2.78 | K64: =I64*J64 -> 55.6 | L64: =G64*G64/162.2 -> 3.8532676 | M64: =(K64*L64*C64) -> 214.24168
B65: Main Bar | C65: 1 | G65: 20 | I65: 8 | J65: 2.78 | K65: =I65*J65 -> 22.24 | L65: =G65*G65/162.2 -> 2.4660912 | M65: =(K65*L65*C65) -> 54.845869
B66: Main Bar | C66: 1 | G66: 16 | I66: 2 | J66: 2.78 | K66: =I66*J66 -> 5.56 | L66: =G66*G66/162.2 -> 1.5782984 | M66: =(K66*L66*C66) -> 8.7753391
B67: Main Bar | C67: 1 | G67: 12 | I67: 6 | J67: 2.78 | K67: =I67*J67 -> 16.68 | L67: =G67*G67/162.2 -> 0.88779285 | M67: =(K67*L67*C67) -> 14.808385
A68: PEDASTAL STIRRUPS STEEL
A69: 1 | B69: P1
B70: Stirrups 1 | C70: 4 | F70: 0.5*0.9 | G70: 8 | H70: 100 | I70: =ROUND(3.33/0.1+1,0) -> 34 | J70: 2.63 | K70: =I70*J70 -> 89.42 | L70: =G70*G70/162.2 -> 0.3945746 | M70: =(K70*L70*C70) -> 141.13144
B71: Stirrups 2 | C71: 4 | G71: 8 | H71: 100 | I71: =ROUND(3.33/0.1+1,0) -> 34 | J71: 1.2 | K71: =I71*J71 -> 40.8 | L71: =G71*G71/162.2 -> 0.3945746 | M71: =(K71*L71*C71) -> 64.394575
B72: Stirrups 3 | C72: 4 | G72: 8 | H72: 100 | I72: =ROUND(3.33/0.1+1,0) -> 34 | J72: 1.2 | K72: =I72*J72 -> 40.8 | L72: =G72*G72/162.2 -> 0.3945746 | M72: =(K72*L72*C72) -> 64.394575
B73: Link 1 | C73: 4 | G73: 8 | H73: 100 | I73: =ROUND(3.33/0.1+1,0) -> 34 | J73: 0.57 | K73: =I73*J73 -> 19.38 | L73: =G73*G73/162.2 -> 0.3945746 | M73: =(K73*L73*C73) -> 30.587423
B74: Link 2 | C74: 4 | G74: 8 | H74: 100 | I74: =ROUND(3.33/0.1+1,0) -> 34 | J74: 0.57 | K74: =I74*J74 -> 19.38 | L74: =G74*G74/162.2 -> 0.3945746 | M74: =(K74*L74*C74) -> 30.587423
B75: Link 3 | C75: 4 | G75: 8 | H75: 100 | I75: =ROUND(3.33/0.1+1,0) -> 34 | J75: 0.57 | K75: =I75*J75 -> 19.38 | L75: =G75*G75/162.2 -> 0.3945746 | M75: =(K75*L75*C75) -> 30.587423
B76: Link 4 | C76: 4 | G76: 8 | H76: 100 | I76: =ROUND(3.33/0.1+1,0) -> 34 | J76: 0.97 | K76: =I76*J76 -> 32.98 | L76: =G76*G76/162.2 -> 0.3945746 | M76: =(K76*L76*C76) -> 52.052281
B77: Link 5 | C77: 4 | G77: 8 | H77: 100 | I77: =ROUND(3.33/0.1+1,0) -> 34 | J77: 0.97 | K77: =I77*J77 -> 32.98 | L77: =G77*G77/162.2 -> 0.3945746 | M77: =(K77*L77*C77) -> 52.052281
A78: 2 | B78: P2
B79: Stirrups 1 | C79: 2 | F79: 0.55*0.55 | G79: 8 | H79: 100 | I79: =ROUND(2.48/0.1+1,0) -> 26 | J79: 2.04 | K79: =I79*J79 -> 53.04 | L79: =G79*G79/162.2 -> 0.3945746 | M79: =(K79*L79*C79) -> 41.856473
B80: Stirrups 2 | C80: 2 | G80: 8 | H80: 100 | I80: =ROUND(2.48/0.1+1,0) -> 26 | J80: 1.34 | K80: =I80*J80 -> 34.84 | L80: =G80*G80/162.2 -> 0.3945746 | M80: =(K80*L80*C80) -> 27.493958
B81: Stirrups 3 | C81: 2 | G81: 8 | H81: 100 | I81: =ROUND(2.48/0.1+1,0) -> 26 | J81: 1.34 | K81: =I81*J81 -> 34.84 | L81: =G81*G81/162.2 -> 0.3945746 | M81: =(K81*L81*C81) -> 27.493958
B82: Link 1 | C82: 2 | G82: 8 | H82: 100 | I82: =ROUND(2.48/0.1+1,0) -> 26 | J82: 0.63 | K82: =I82*J82 -> 16.38 | L82: =G82*G82/162.2 -> 0.3945746 | M82: =(K82*L82*C82) -> 12.926264
B83: Link 2 | C83: 2 | G83: 8 | H83: 100 | I83: =ROUND(2.48/0.1+1,0) -> 26 | J83: 0.63 | K83: =I83*J83 -> 16.38 | L83: =G83*G83/162.2 -> 0.3945746 | M83: =(K83*L83*C83) -> 12.926264
A84: 3 | B84: P3 | F84: 0.65*0.65
B85: Stirrups 1 | C85: 2 | G85: 8 | H85: 100 | I85: =ROUND(2.48/0.1+1,0) -> 26 | J85: 2.44 | K85: =I85*J85 -> 63.44 | L85: =G85*G85/162.2 -> 0.3945746 | M85: =(K85*L85*C85) -> 50.063625
B86: Stirrups 2 | C86: 2 | G86: 8 | H86: 100 | I86: =ROUND(2.48/0.1+1,0) -> 26 | J86: 1.53 | K86: =I86*J86 -> 39.78 | L86: =G86*G86/162.2 -> 0.3945746 | M86: =(K86*L86*C86) -> 31.392355
B87: Stirrups 3 | C87: 2 | G87: 8 | H87: 100 | I87: =ROUND(2.48/0.1+1,0) -> 26 | J87: 1.53 | K87: =I87*J87 -> 39.78 | L87: =G87*G87/162.2 -> 0.3945746 | M87: =(K87*L87*C87) -> 31.392355
B88: Stirrups 4 | C88: 2 | G88: 8 | H88: 100 | I88: =ROUND(2.48/0.1+1,0) -> 26 | J88: 1.53 | K88: =I88*J88 -> 39.78 | L88: =G88*G88/162.2 -> 0.3945746 | M88: =(K88*L88*C88) -> 31.392355
B89: Stirrups 5 | C89: 2 | G89: 8 | H89: 100 | I89: =ROUND(2.48/0.1+1,0) -> 26 | J89: 1.53 | K89: =I89*J89 -> 39.78 | L89: =G89*G89/162.2 -> 0.3945746 | M89: =(K89*L89*C89) -> 31.392355
A90: 4 | B90: P4 | F90: 0.8*0.8
B91: Stirrups 1 | C91: 2 | G91: 8 | H91: 100 | I91: =ROUND(2.48/0.1+1,0) -> 26 | J91: 3.04 | K91: =I91*J91 -> 79.04 | L91: =G91*G91/162.2 -> 0.3945746 | M91: =(K91*L91*C91) -> 62.374353
B92: Stirrups 2 | C92: 2 | G92: 8 | H92: 100 | I92: =ROUND(2.48/0.1+1,0) -> 26 | J92: 1.81 | K92: =I92*J92 -> 47.06 | L92: =G92*G92/162.2 -> 0.3945746 | M92: =(K92*L92*C92) -> 37.137361
B93: Stirrups 3 | C93: 2 | G93: 8 | H93: 100 | I93: =ROUND(2.48/0.1+1,0) -> 26 | J93: 1.81 | K93: =I93*J93 -> 47.06 | L93: =G93*G93/162.2 -> 0.3945746 | M93: =(K93*L93*C93) -> 37.137361
B94: Stirrups 4 | C94: 2 | G94: 8 | H94: 100 | I94: =ROUND(2.48/0.1+1,0) -> 26 | J94: 1.81 | K94: =I94*J94 -> 47.06 | L94: =G94*G94/162.2 -> 0.3945746 | M94: =(K94*L94*C94) -> 37.137361
B95: Stirrups 5 | C95: 2 | G95: 8 | H95: 100 | I95: =ROUND(2.48/0.1+1,0) -> 26 | J95: 1.81 | K95: =I95*J95 -> 47.06 | L95: =G95*G95/162.2 -> 0.3945746 | M95: =(K95*L95*C95) -> 37.137361
B96: Link 1 | C96: 2 | G96: 8 | H96: 100 | I96: =ROUND(2.48/0.1+1,0) -> 26 | J96: 0.88 | K96: =I96*J96 -> 22.88 | L96: =G96*G96/162.2 -> 0.3945746 | M96: =(K96*L96*C96) -> 18.055734
B97: Link 2 | C97: 2 | G97: 8 | H97: 100 | I97: =ROUND(2.48/0.1+1,0) -> 26 | J97: 0.88 | K97: =I97*J97 -> 22.88 | L97: =G97*G97/162.2 -> 0.3945746 | M97: =(K97*L97*C97) -> 18.055734
B98: Link 3 | C98: 2 | G98: 8 | H98: 100 | I98: =ROUND(2.48/0.1+1,0) -> 26 | J98: 0.88 | K98: =I98*J98 -> 22.88 | L98: =G98*G98/162.2 -> 0.3945746 | M98: =(K98*L98*C98) -> 18.055734
B99: Link 4 | C99: 2 | G99: 8 | H99: 100 | I99: =ROUND(2.48/0.1+1,0) -> 26 | J99: 0.88 | K99: =I99*J99 -> 22.88 | L99: =G99*G99/162.2 -> 0.3945746 | M99: =(K99*L99*C99) -> 18.055734
B100: Link 5 | C100: 2 | G100: 8 | H100: 100 | I100: =ROUND(2.48/0.1+1,0) -> 26 | J100: 0.88 | K100: =I100*J100 -> 22.88 | L100: =G100*G100/162.2 -> 0.3945746 | M100: =(K100*L100*C100) -> 18.055734
...
